LICENSE
aiotgnotifier/__init__.py
aiotgnotifier/_message.py
aiotgnotifier/_notifier.py
aiotgnotifier-0.1.0.dist-info/LICENSE
aiotgnotifier-0.1.0.dist-info/WHEEL
aiotgnotifier-0.1.0.dist-info/METADATA
aiotgnotifier-0.1.0.dist-info/RECORD
